neovortex/__init__.py
neovortex/async_client.py
neovortex/batch.py
neovortex/cli.py
neovortex/client.py
neovortex/exceptions.py
neovortex/hooks.py
neovortex/middleware.py
neovortex/models.py
neovortex/offline.py
neovortex/ratelimit.py
neovortex/request.py
neovortex/response.py
neovortex/validator.py
neovortex/auth/__init__.py
neovortex/auth/api_key.py
neovortex/auth/base.py
neovortex/auth/jwt.py
neovortex/auth/oauth.py
neovortex/plugins/__init__.py
neovortex/plugins/caching.py
neovortex/plugins/logging.py
neovortex/plugins/metrics.py
neovortex/plugins/registry.py
neovortex/plugins/custom/__init__.py
neovortex/plugins/custom/api_key_rotation.py
neovortex/plugins/custom/aws4_auth.py
neovortex/plugins/custom/caching.py
neovortex/plugins/custom/cdn_proxy.py
neovortex/plugins/custom/compression.py
neovortex/plugins/custom/dynamic_throttle.py
neovortex/plugins/custom/etag_cache.py
neovortex/plugins/custom/graphql.py
neovortex/plugins/custom/sentry.py
neovortex/plugins/custom/xml_to_json.py
neovortex/utils/__init__.py
neovortex/utils/priority_queue.py
neovortex/utils/rate_limiter.py
neovortex/utils/retry.py
neovortex/utils/security.py
neovortex/utils/sse.py
neovortex/utils/validation.py
neovortex/utils/websocket.py
neovortex-1.0.2.dist-info/licenses/LICENSE
tests/__init__.py
tests/conftest.py
tests/test_async_client.py
tests/test_auth.py
tests/test_client.py
tests/test_middleware.py
tests/test_plugins.py
tests/test_utils.py
neovortex-1.0.2.dist-info/METADATA
neovortex-1.0.2.dist-info/WHEEL
neovortex-1.0.2.dist-info/entry_points.txt
neovortex-1.0.2.dist-info/top_level.txt
neovortex-1.0.2.dist-info/RECORD
